{
  "$schema": "https://static.modelcontextprotocol.io/schemas/2025-12-11/server.schema.json",
  "name": "io.github.vaaraio/vaara-server",
  "title": "Vaara MCP Server",
  "description": "EU AI Act runtime evidence as a standalone MCP server: gating, tamper-evident audit",
  "websiteUrl": "https://vaara.io",
  "repository": {
    "url": "https://github.com/vaaraio/vaara",
    "source": "github"
  },
  "version": "1.17.0",
  "packages": [
    {
      "registryType": "pypi",
      "registryBaseUrl": "https://pypi.org",
      "identifier": "vaara",
      "version": "1.17.0",
      "runtimeHint": "uvx",
      "transport": {
        "type": "stdio"
      },
      "runtimeArguments": [
        {
          "type": "named",
          "name": "--from",
          "value": "vaara",
          "description": "PyPI package providing the vaara-mcp-server entry point"
        },
        {
          "type": "positional",
          "value": "vaara-mcp-server"
        }
      ],
      "environmentVariables": [
        {
          "name": "VAARA_DB",
          "description": "Path to the SQLite audit DB. Defaults to vaara_audit.db in the working directory.",
          "isRequired": false
        },
        {
          "name": "VAARA_API_KEY",
          "description": "Optional shared secret. When set, every tool call must include _api_key in its arguments. Leave unset for single-tenant stdio deployments where process isolation is enough.",
          "isRequired": false
        }
      ]
    }
  ]
}
